MANIFEST.in
README.txt
setup.py
collective/__init__.py
collective.contentfiles2aws.egg-info/PKG-INFO
collective.contentfiles2aws.egg-info/SOURCES.txt
collective.contentfiles2aws.egg-info/dependency_links.txt
collective.contentfiles2aws.egg-info/entry_points.txt
collective.contentfiles2aws.egg-info/namespace_packages.txt
collective.contentfiles2aws.egg-info/not-zip-safe
collective.contentfiles2aws.egg-info/requires.txt
collective.contentfiles2aws.egg-info/top_level.txt
collective/contentfiles2aws/__init__.py
collective/contentfiles2aws/awsfile.py
collective/contentfiles2aws/catalog.py
collective/contentfiles2aws/catalog.zcml
collective/contentfiles2aws/config.py
collective/contentfiles2aws/configure.zcml
collective/contentfiles2aws/content_types_patch.py
collective/contentfiles2aws/fields.py
collective/contentfiles2aws/handlers.py
collective/contentfiles2aws/profiles.zcml
collective/contentfiles2aws/skins.zcml
collective/contentfiles2aws/storage.py
collective/contentfiles2aws/subscribers.zcml
collective/contentfiles2aws/testing.py
collective/contentfiles2aws/upgrades.py
collective/contentfiles2aws/upgrades.zcml
collective/contentfiles2aws/utility.py
collective/contentfiles2aws/utility.zcml
collective/contentfiles2aws/utils.py
collective/contentfiles2aws/widgets.py
collective/contentfiles2aws/browser/__init__.py
collective/contentfiles2aws/browser/configure.zcml
collective/contentfiles2aws/browser/content_migration.py
collective/contentfiles2aws/browser/util.py
collective/contentfiles2aws/client/__init__.py
collective/contentfiles2aws/client/awsclient.py
collective/contentfiles2aws/client/fsclient.py
collective/contentfiles2aws/client/interfaces/__init__.py
collective/contentfiles2aws/client/interfaces/awsclient.py
collective/contentfiles2aws/client/interfaces/fsclient.py
collective/contentfiles2aws/content/__init__.py
collective/contentfiles2aws/content/awsfile.py
collective/contentfiles2aws/content/awsimage.py
collective/contentfiles2aws/content/interfaces.py
collective/contentfiles2aws/dtml/imageAdd.dtml
collective/contentfiles2aws/images/File_icon.gif
collective/contentfiles2aws/images/Image_icon.gif
collective/contentfiles2aws/interfaces/__init__.py
collective/contentfiles2aws/interfaces/fields.py
collective/contentfiles2aws/interfaces/utility.py
collective/contentfiles2aws/profiles/default/catalog.xml
collective/contentfiles2aws/profiles/default/factorytool.xml
