Metadata-Version: 1.0
Name: collective.contentfiles2aws
Version: 1.3.0
Summary: Allows to store files and images on amazon s3 service.
Home-page: https://github.com/martinschoel/collective.contentfiles2aws.git
Author: Taras Melnychuk
Author-email: melnychuktaras@gmail.com
License: GPL
Keywords: Plone AWS
Platform: UNKNOWN
Classifier: Programming Language :: Python
